MANIFEST.in
setup.cfg
setup.py
versioneer.py
learners/__init__.py
learners/_version.py
learners/channels.py
learners/learner.py
learners/nn_set.py
learners/tools.py
learners.egg-info/PKG-INFO
learners.egg-info/SOURCES.txt
learners.egg-info/dependency_links.txt
learners.egg-info/not-zip-safe
learners.egg-info/pbr.json
learners.egg-info/requires.txt
learners.egg-info/top_level.txt
learners/algorithms/__init__.py
learners/algorithms/avgnn.py
learners/algorithms/imle_model.py
learners/algorithms/lwlr.py
learners/algorithms/lwlr_cpp.py
learners/algorithms/mutate_nn.py
learners/algorithms/nn.py
learners/algorithms/optimize.py
learners/algorithms/predict_mutate.py
learners/algorithms/rand.py
learners/algorithms/wnn.py
learners/operators/__init__.py
learners/operators/mutation_op.py