Metadata-Version: 1.1
Name: learners
Version: 1.0.4
Summary: A collection of simple incremental forward and inverse model learning algorithms
Home-page: github.com/humm/learners.git
Author: Fabien Benureau
Author-email: fabien.benureau@gmail.com
License: Open Science License (see fabien.benureau.com/openscience.html)
Download-URL: https://github.com/humm/learners/tarball/1.0.4
Keywords: learning algorithm
Platform: UNKNOWN
